datatracker/__init__.py
datatracker/_version.py
datatracker/dictlist.py
datatracker/entry.py
datatracker/file.py
datatracker/schema.py
datatracker/tracker.py
datatracker/utils.py
datatracker/utils_async.py
datatracker-0.2.5.dist-info/LICENSE.md
datatracker-0.2.5.dist-info/METADATA
datatracker-0.2.5.dist-info/WHEEL
datatracker-0.2.5.dist-info/top_level.txt
datatracker-0.2.5.dist-info/RECORD
