Metadata-Version: 2.1
Name: datatracker
Version: 0.2.5
Summary: Methods to help track the scripts and datafiles in a project.
Home-page: https://github.com/TarjinderSingh/datatracker
Author: TarjinderSingh
Author-email: tsingh@broadinstitute.org
License: MIT
Platform: UNKNOWN
Requires-Python: >=3.7
License-File: LICENSE.md
Requires-Dist: autopep8 (>=1.5.4)
Requires-Dist: versioneer (>=0.18)
Requires-Dist: logzero (>=1.5.0)
Requires-Dist: tinydb (>=4.1.0)
Requires-Dist: pandas (>=1.0.0)
Requires-Dist: openpyxl (>=3.0.5)
